wm_faiss/__init__.py
wm_faiss/faiss_knn.py
wm_faiss-1.0.0.dist-info/LICENSE
wm_faiss-1.0.0.dist-info/METADATA
wm_faiss-1.0.0.dist-info/WHEEL
wm_faiss-1.0.0.dist-info/top_level.txt
wm_faiss-1.0.0.dist-info/RECORD
